webgpu_fonts/__init__.py
webgpu_fonts/__main__.py
webgpu_fonts/_version.py
webgpu_fonts/generate_font_file.py
webgpu_fonts/fonts/fira-regular.bin
webgpu_fonts-0.0.1.dist-info/METADATA
webgpu_fonts-0.0.1.dist-info/WHEEL
webgpu_fonts-0.0.1.dist-info/top_level.txt
webgpu_fonts-0.0.1.dist-info/RECORD
